llmrouter/__init__.py
llmrouter/plugin_system.py
llmrouter/cli/__init__.py
llmrouter/cli/router_chat.py
llmrouter/cli/router_inference.py
llmrouter/cli/router_main.py
llmrouter/cli/router_train.py
llmrouter/data/__init__.py
llmrouter/data/api_calling_evaluation.py
llmrouter/data/data.py
llmrouter/data/data_generation.py
llmrouter/data/data_loader.py
llmrouter/data/generate_llm_embeddings.py
llmrouter/data/multimodal_generation.py
llmrouter/evaluation/__init__.py
llmrouter/evaluation/batch_evaluator.py
llmrouter/evaluation/example.py
llmrouter/models/__init__.py
llmrouter/models/base_trainer.py
llmrouter/models/meta_router.py
llmrouter/models/automix/__init__.py
llmrouter/models/automix/data_pipeline.py
llmrouter/models/automix/main_automix.py
llmrouter/models/automix/methods.py
llmrouter/models/automix/model.py
llmrouter/models/automix/router.py
llmrouter/models/automix/trainer.py
llmrouter/models/causallm_router/__init__.py
llmrouter/models/causallm_router/router.py
llmrouter/models/causallm_router/trainer.py
llmrouter/models/elorouter/__init__.py
llmrouter/models/elorouter/router.py
llmrouter/models/elorouter/trainer.py
llmrouter/models/gmtrouter/__init__.py
llmrouter/models/gmtrouter/data_loader.py
llmrouter/models/gmtrouter/models.py
llmrouter/models/gmtrouter/router.py
llmrouter/models/gmtrouter/trainer.py
llmrouter/models/graphrouter/__init__.py
llmrouter/models/graphrouter/graph_nn.py
llmrouter/models/graphrouter/router.py
llmrouter/models/graphrouter/trainer.py
llmrouter/models/hybrid_llm/__init__.py
llmrouter/models/hybrid_llm/router.py
llmrouter/models/hybrid_llm/trainer.py
llmrouter/models/knnmultiroundrouter/__init__.py
llmrouter/models/knnmultiroundrouter/router.py
llmrouter/models/knnmultiroundrouter/trainer.py
llmrouter/models/knnrouter/__init__.py
llmrouter/models/knnrouter/router.py
llmrouter/models/knnrouter/trainer.py
llmrouter/models/largest_llm/__init__.py
llmrouter/models/largest_llm/router.py
llmrouter/models/llmmultiroundrouter/__init__.py
llmrouter_lib-0.2.0.dist-info/licenses/LICENSE
llmrouter_lib-0.2.0.dist-info/METADATA
llmrouter_lib-0.2.0.dist-info/WHEEL
llmrouter_lib-0.2.0.dist-info/entry_points.txt
llmrouter_lib-0.2.0.dist-info/top_level.txt
llmrouter_lib-0.2.0.dist-info/RECORD
