Metadata-Version: 2.4
Name: llmrouter-lib
Version: 0.2.0
Summary: A unified framework for LLM routing and evaluation.
Author-email: Tao Feng <taofeng2@illinois.edu>, Haozhen Zhang <wazhz14@gmail.com>
License: MIT License
Project-URL: Homepage, https://github.com/ulab-uiuc/LLMRouter
Project-URL: Source, https://github.com/ulab-uiuc/LLMRouter
Project-URL: Bug Tracker, https://github.com/ulab-uiuc/LLMRouter/issues
Classifier: Programming Language :: Python :: 3
Classifier: Programming Language :: Python :: 3.10
Classifier: Programming Language :: Python :: 3.11
Classifier: License :: OSI Approved :: MIT License
Classifier: Operating System :: OS Independent
Classifier: Development Status :: 3 - Alpha
Classifier: Intended Audience :: Developers
Classifier: Intended Audience :: Science/Research
Classifier: Topic :: Scientific/Engineering :: Artificial Intelligence
Requires-Python: >=3.10
License-File: LICENSE
Requires-Dist: torch>=2.0
Requires-Dist: transformers>=4.40
Requires-Dist: sentencepiece>=0.1.99
Requires-Dist: numpy>=1.21
Requires-Dist: pandas>=1.5
Requires-Dist: scikit-learn>=1.2
Requires-Dist: pyyaml>=6.0
Requires-Dist: tqdm>=4.65
Requires-Dist: datasets>=2.14
Requires-Dist: pydantic>=2.0
Requires-Dist: gradio>=4.0
Requires-Dist: litellm>=1.0
Requires-Dist: peft>=0.7
Requires-Dist: torch-geometric>=2.3
Requires-Dist: scipy>=1.10
Requires-Dist: protobuf>=3.20
Provides-Extra: router-r1
Requires-Dist: vllm==0.6.3; extra == "router-r1"
Requires-Dist: torch==2.4.0; extra == "router-r1"
Requires-Dist: openai>=1.0; extra == "router-r1"
Provides-Extra: all
Requires-Dist: vllm==0.6.3; extra == "all"
Requires-Dist: torch==2.4.0; extra == "all"
Requires-Dist: openai>=1.0; extra == "all"
Dynamic: license-file
